baiduads_manual/__init__.py
baiduads_manual/marketingfile/__init__.py
baiduads_manual/marketingfile/api/__init__.py
baiduads_manual/marketingfile/api/marketing_file_service.py
baiduads_manual/marketingfile/model/__init__.py
baiduads_manual/marketingfile/model/upload_file_info.py
baiduads_manual/marketingfile/model/upload_file_params.py
baiduads_manual/marketingfile/model/upload_file_request.py
baiduads_manual/marketingfile/model/upload_file_request_wrapper.py
baiduads_manual/marketingfile/model/upload_file_response.py
baiduads_manual/marketingfile/model/upload_file_response_wrapper.py
baiduads_manual/oauth/__init__.py
baiduads_manual/oauth/api/__init__.py
baiduads_manual/oauth/api/oauth_service.py
baiduads_manual/oauth/model/__init__.py
baiduads_manual/oauth/model/access_token_info.py
baiduads_manual/oauth/model/get_access_token_request.py
baiduads_manual/oauth/model/get_access_token_response.py
baiduads_manual/oauth/model/get_open_id_request.py
baiduads_manual/oauth/model/get_open_id_response.py
baiduads_manual/oauth/model/get_user_info_request.py
baiduads_manual/oauth/model/get_user_info_response.py
baiduads_manual/oauth/model/open_id_info.py
baiduads_manual/oauth/model/refresh_token_request.py
baiduads_manual/oauth/model/refresh_token_response.py
baiduads_manual/oauth/model/sub_user_info.py
baiduads_manual/oauth/model/user_info.py
baiduads_manual/upload/__init__.py
baiduads_manual/upload/mulitupload_options.py
baiduads_manual/upload/upload_client.py
baiduads_manual/videoupload/__init__.py
baiduads_manual/videoupload/api/__init__.py
baiduads_manual/videoupload/api/video_upload_service.py
baiduads_manual/videoupload/model/__init__.py
baiduads_manual/videoupload/model/add_video_params.py
baiduads_manual/videoupload/model/add_video_request.py
baiduads_manual/videoupload/model/add_video_request_wrapper.py
baiduads_manual/videoupload/model/add_video_response.py
baiduads_manual/videoupload/model/add_video_response_wrapper.py
baiduads_sdk-2023.1.0.dist-info/METADATA
baiduads_sdk-2023.1.0.dist-info/WHEEL
baiduads_sdk-2023.1.0.dist-info/top_level.txt
baiduads_sdk-2023.1.0.dist-info/RECORD
