Metadata-Version: 2.1
Name: baiduads-sdk
Version: 2023.1.0
Summary: baiduads-sdk
Home-page: 
Author: baidu
Author-email: jiangyuan04@baidu.com
Keywords: baidu
Requires-Python: >=3.6
Requires-Dist: baiduads-sdk-auto (>=2023.1.0)
